pyw/__init__.py
pyw/fs/__init__.py
pyw_fs-0.0.0.post2.dist-info/METADATA
pyw_fs-0.0.0.post2.dist-info/WHEEL
pyw_fs-0.0.0.post2.dist-info/licenses/LICENSE
pyw_fs-0.0.0.post2.dist-info/RECORD
